pfsense_vshell/__init__.py
pfsense_vshell-2.2.3.data/scripts/pfsense-vshell
pfsense_vshell-2.2.3.dist-info/licenses/LICENSE
pfsense_vshell-2.2.3.dist-info/METADATA
pfsense_vshell-2.2.3.dist-info/WHEEL
pfsense_vshell-2.2.3.dist-info/top_level.txt
pfsense_vshell-2.2.3.dist-info/RECORD
