Metadata-Version: 2.4
Name: pfsense-vshell
Version: 2.2.3
Summary: A command line tool to run remote shell commands on pfSense without SSH.
Home-page: https://github.com/jaredhendrickson13/pfsense-vshell
Author: Jared Hendrickson
Author-email: github@jaredhendrickson.com
License: Apache-2.0
Classifier: Programming Language :: Python :: 3
Classifier: License :: OSI Approved :: Apache Software License
Classifier: Operating System :: OS Independent
Requires-Python: >=3.5
License-File: LICENSE
Requires-Dist: requests~=2.32.5
Requires-Dist: urllib3~=2.6.0
Dynamic: author
Dynamic: author-email
Dynamic: classifier
Dynamic: description
Dynamic: description-content-type
Dynamic: home-page
Dynamic: license
Dynamic: license-file
Dynamic: requires-dist
Dynamic: requires-python
Dynamic: summary
